bitbee/__init__.py
bitbee/bitbee.py
bitbee/model.py
bit_bee-1.0.1.dist-info/LICENSE
bit_bee-1.0.1.dist-info/METADATA
bit_bee-1.0.1.dist-info/WHEEL
bit_bee-1.0.1.dist-info/top_level.txt
bit_bee-1.0.1.dist-info/RECORD
