Metadata-Version: 2.1
Name: bit-bee
Version: 1.0.1
Summary: bit-bee api client
Home-page: https://github.com/fatelei/bit-bee
Author: fatelei
Author-email: fatelei@gmail.com
License: UNKNOWN
Project-URL: Bug Tracker, https://github.com/fatelei/bit-bee/issues
Platform: UNKNOWN
Classifier: Programming Language :: Python :: 3
Classifier: License :: OSI Approved :: MIT License
Classifier: Operating System :: OS Independent
Requires-Python: >=3.6
License-File: LICENSE
Requires-Dist: requests
